bare_cli/__init__.py
bare_cli/bare_cli.py
bare_cli/color_mapper.py
bare_cli/enums.py
bare_cli/invalid_choice_error.py
bare_cli/blocks/abstract_block.py
bare_cli/blocks/choice_block.py
bare_cli/blocks/misc_block.py
bare_cli/blocks/nested_status_block.py
bare_cli/blocks/status_block.py
bare_cli-1.0.1.dist-info/licenses/LICENSE
bare_cli-1.0.1.dist-info/licenses/NOTICE
bare_cli-1.0.1.dist-info/METADATA
bare_cli-1.0.1.dist-info/WHEEL
bare_cli-1.0.1.dist-info/top_level.txt
bare_cli-1.0.1.dist-info/RECORD
