Metadata-Version: 2.4
Name: bare-cli
Version: 1.0.1
Summary: May your CLI code be semantic and your text output beautifully bare.
Author-email: Jamison Griffith <jamison.griffith@gmail.com>
License-Expression: Apache-2.0
Project-URL: Homepage, https://github.com/jamogriff/bare-cli
Project-URL: Documentation, https://github.com/jamogriff/bare-cli/blob/main/README.md
Project-URL: Source, https://github.com/jamogriff/bare-cli
Project-URL: Issues, https://github.com/jamogriff/bare-cli/issues
Keywords: cli,color,colors,terminal,console,ansi,style,styles,text,command-line,formatting
Classifier: Intended Audience :: Developers
Classifier: Development Status :: 5 - Production/Stable
Classifier: Operating System :: OS Independent
Classifier: Programming Language :: Python :: 3.10
Classifier: Programming Language :: Python :: 3.15
Classifier: Topic :: Software Development
Classifier: Topic :: Software Development :: Libraries :: Python Modules
Classifier: Topic :: Terminals
Classifier: Topic :: Utilities
Requires-Python: >=3.10
License-File: LICENSE
License-File: NOTICE
Requires-Dist: colorama>=0.4.6
Dynamic: license-file
